commonroad/__init__.py
commonroad/common/__init__.py
commonroad/common/common_lanelet.py
commonroad/common/file_reader.py
commonroad/common/file_writer.py
commonroad/common/reader/__init__.py
commonroad/common/reader/file_reader_interface.py
commonroad/common/reader/file_reader_protobuf.py
commonroad/common/reader/file_reader_xml.py
commonroad/common/solution.py
commonroad/common/util.py
commonroad/common/validity.py
commonroad/common/writer/__init__.py
commonroad/common/writer/file_writer_interface.py
commonroad/common/writer/file_writer_protobuf.py
commonroad/common/writer/file_writer_xml.py
commonroad/geometry/__init__.py
commonroad/geometry/polyline_util.py
commonroad/geometry/shape.py
commonroad/geometry/transform.py
commonroad/planning/__init__.py
commonroad/planning/goal.py
commonroad/planning/planner_interface.py
commonroad/planning/planning_problem.py
commonroad/prediction/__init__.py
commonroad/prediction/ground_truth_predictor.py
commonroad/prediction/prediction.py
commonroad/prediction/prediction_interface.py
commonroad/scenario/__init__.py
commonroad/scenario/area.py
commonroad/scenario/intersection.py
commonroad/scenario/lanelet.py
commonroad/scenario/obstacle.py
commonroad/scenario/scenario.py
commonroad/scenario/state.py
commonroad/scenario/traffic_light.py
commonroad/scenario/traffic_sign.py
commonroad/scenario/traffic_sign_interpreter.py
commonroad/scenario/trajectory.py
commonroad/scenario_definition/__init__.py
commonroad/scenario_definition/protobuf_format/__init__.py
commonroad/scenario_definition/protobuf_format/definition_files/commonroad.proto
commonroad/scenario_definition/protobuf_format/definition_files/dynamic_obstacle.proto
commonroad/scenario_definition/protobuf_format/definition_files/environment_obstacle.proto
commonroad/scenario_definition/protobuf_format/definition_files/intersection.proto
commonroad/scenario_definition/protobuf_format/definition_files/lanelet.proto
commonroad_io-2024.3.dist-info/LICENSE.txt
commonroad_io-2024.3.dist-info/METADATA
commonroad_io-2024.3.dist-info/WHEEL
commonroad_io-2024.3.dist-info/RECORD
