Metadata-Version: 2.1
Name: commonroad-io
Version: 2024.3
Summary: Python tool to read, write, and visualize CommonRoad scenarios and solutions for automated vehicles.
Home-page: https://commonroad.in.tum.de
License: BSD
Keywords: autonomous,automated,vehicles,driving,motion,planning
Author: Cyber-Physical Systems Group, Technical University of Munich
Author-email: commonroad@lists.lrz.de
Requires-Python: >=3.9,<4.0
Classifier: License :: OSI Approved :: BSD License
Classifier: License :: Other/Proprietary License
Classifier: Operating System :: MacOS
Classifier: Operating System :: Microsoft :: Windows
Classifier: Operating System :: POSIX :: Linux
Classifier: Programming Language :: Python :: 3
Classifier: Programming Language :: Python :: 3.9
Classifier: Programming Language :: Python :: 3.10
Classifier: Programming Language :: Python :: 3.11
Classifier: Programming Language :: Python :: 3.12
Classifier: Programming Language :: Python :: 3.13
Requires-Dist: commonroad-vehicle-models (>=2.0.0)
Requires-Dist: iso3166 (>=1.0.1)
Requires-Dist: lxml (>=4.2.2)
Requires-Dist: matplotlib (>=3.0.0)
Requires-Dist: networkx (>=2.2)
Requires-Dist: numpy (>=1.26.1) ; python_version < "3.13"
Requires-Dist: numpy (>=2.1.0) ; python_version >= "3.13"
Requires-Dist: omegaconf (>=2.0)
Requires-Dist: pillow (>=10.4.0)
Requires-Dist: protobuf (==3.20.2)
Requires-Dist: rtree (>=0.8.3)
Requires-Dist: scipy (>=1.11.3) ; python_version < "3.13"
Requires-Dist: scipy (>=1.13.0) ; python_version >= "3.13"
Requires-Dist: shapely (>=2.0.1,<3.0.0)
Requires-Dist: tqdm (>=4.64)
Project-URL: Documentation, https://cps.pages.gitlab.lrz.de/commonroad/commonroad-io/
Project-URL: Forum, https://github.com/orgs/CommonRoad/discussions
Project-URL: Source, https://github.com/CommonRoad/commonroad-io
